quartet_output/__init__.py
quartet_output/admin.py
quartet_output/apps.py
quartet_output/errors.py
quartet_output/evaluation.py
quartet_output/models.py
quartet_output/parsing.py
quartet_output/permissions.py
quartet_output/routers.py
quartet_output/rules.py
quartet_output/serializers.py
quartet_output/steps.py
quartet_output/urls.py
quartet_output/views.py
quartet_output/viewsets.py
quartet_output/management/__init__.py
quartet_output/management/commands/__init__.py
quartet_output/management/commands/create_output_groups.py
quartet_output/management/commands/load_output_rules.py
quartet_output/management/commands/utils.py
quartet_output/migrations/0001_initial.py
quartet_output/migrations/0002_auto_20180909_0946.py
quartet_output/migrations/0003_auto_20190214_1806.py
quartet_output/migrations/0004_auto_20190725_1122.py
quartet_output/migrations/0005_auto_20200824_1624.py
quartet_output/migrations/0006_alter_authenticationinfo_id_alter_endpoint_id_and_more.py
quartet_output/migrations/__init__.py
quartet_output/transport/__init__.py
quartet_output/transport/http.py
quartet_output/transport/mail.py
quartet_output/transport/sftp.py
quartet_output/transport/tcp.py
tests/__init__.py
tests/settings.py
tests/test_agg_trigger.py
tests/test_rules.py
tests/test_views.py
tests/urls.py
quartet_output-4.0.0.dist-info/AUTHORS.rst
quartet_output-4.0.0.dist-info/LICENSE
quartet_output-4.0.0.dist-info/METADATA
quartet_output-4.0.0.dist-info/WHEEL
quartet_output-4.0.0.dist-info/top_level.txt
quartet_output-4.0.0.dist-info/RECORD
