Metadata-Version: 2.1
Name: quartet-output
Version: 4.0.0
Summary: Output logic for QU4RTET supply chain messaging.
Home-page: https://gitlab.com/serial-lab/quartet_output
Author: Rob Magee
Author-email: slab@serial-lab.com
License: MIT
Keywords: quartet_output
Platform: UNKNOWN
Classifier: Development Status :: 5 - Production/Stable
Classifier: Framework :: Django
Classifier: Framework :: Django :: 2.0
Classifier: Intended Audience :: Healthcare Industry
Classifier: Intended Audience :: Manufacturing
Classifier: Intended Audience :: Developers
Classifier: License :: OSI Approved :: GNU Affero General Public License v3 or later (AGPLv3+)
Classifier: Natural Language :: English
Classifier: Programming Language :: Python :: 3
Classifier: Programming Language :: Python :: 3.5
Classifier: Programming Language :: Python :: 3.6
